streamlit_profiler/__init__.py
streamlit_profiler-0.2.4.dist-info/LICENSE
streamlit_profiler-0.2.4.dist-info/WHEEL
streamlit_profiler-0.2.4.dist-info/METADATA
streamlit_profiler-0.2.4.dist-info/RECORD
